xj_thread/__init__.py
xj_thread/admin.py
xj_thread/apps.py
xj_thread/forms.py
xj_thread/models.py
xj_thread/serializers.py
xj_thread/urls.py
xj_thread/validator.py
xj_thread/views.py
xj_thread/apis/__init__.py
xj_thread/apis/thread_add.py
xj_thread/apis/thread_category_api.py
xj_thread/apis/thread_category_list_api.py
xj_thread/apis/thread_category_tree.py
xj_thread/apis/thread_classify_apis.py
xj_thread/apis/thread_classify_tree.py
xj_thread/apis/thread_item_v3.py
xj_thread/apis/thread_item_v4.py
xj_thread/apis/thread_list [del].py
xj_thread/apis/thread_list-v3.py
xj_thread/apis/thread_list_v4.py
xj_thread/apis/thread_other_list.py
xj_thread/apis/thread_statistic.py
xj_thread/apis/thread_tags_apis.py
xj_thread/libs/DjangoUeditor.py
xj_thread/libs/__init__.py
xj_thread/libs/DjangoUeditor/__init__.py
xj_thread/libs/DjangoUeditor/adminx.py
xj_thread/libs/DjangoUeditor/commands.py
xj_thread/libs/DjangoUeditor/forms.py
xj_thread/libs/DjangoUeditor/models.py
xj_thread/libs/DjangoUeditor/settings.py
xj_thread/libs/DjangoUeditor/urls.py
xj_thread/libs/DjangoUeditor/utils.py
xj_thread/libs/DjangoUeditor/views.py
xj_thread/libs/DjangoUeditor/widgets.py
xj_thread/migrations/0001_initial.py
xj_thread/migrations/0002_alter_thread_user_uuid_alter_thread_uuid_and_more.py
xj_thread/migrations/__init__.py
xj_thread/services/__init__.py
xj_thread/services/thread_auth_service.py
xj_thread/services/thread_category_list_service.py
xj_thread/services/thread_category_service.py
xj_thread/services/thread_category_tree_service [backup].py
xj_thread/services/thread_category_tree_service.py
xj_thread/services/thread_classify_service.py
xj_thread/services/thread_classify_tree_service.py
xj_thread/services/thread_extend_service.py
xj_thread/services/thread_extend_service_v2.py
xj_thread/services/thread_item_service.py
xj_thread/services/thread_item_service_v2.py
xj_thread/services/thread_list_service.py
xj_thread/services/thread_list_service_v2.py
xj_thread-2.0.5.dist-info/METADATA
xj_thread-2.0.5.dist-info/WHEEL
xj_thread-2.0.5.dist-info/top_level.txt
xj_thread-2.0.5.dist-info/RECORD
