Metadata-Version: 2.1
Name: xj_thread
Version: 2.0.5
Summary: 信息模块
License: apache 3.0
Requires-Dist: xj-user
